dataset_format_converter/__init__.py
dataset_format_converter/cli/__init__.py
dataset_format_converter/cli/main.py
dataset_format_converter/config/__init__.py
dataset_format_converter/config/settings.py
dataset_format_converter/core/__init__.py
dataset_format_converter/core/base_format.py
dataset_format_converter/core/common_format.py
dataset_format_converter/core/format_manager.py
dataset_format_converter/core/geometry_utils.py
dataset_format_converter/formats/__init__.py
dataset_format_converter/formats/dota.py
dataset_format_converter/formats/labelimg_obb.py
dataset_format_converter/formats/pascal_voc.py
dataset_format_converter/formats/yolo_hbb.py
dataset_format_converter/formats/yolo_obb.py
dataset_format_converter/gui/__init__.py
dataset_format_converter/gui/main_window.py
dataset_format_converter/i18n/__init__.py
dataset_format_converter/i18n/translation.py
dataset_format_converter/i18n/locales/__init__.py
dataset_format_converter/i18n/locales/en.json
dataset_format_converter/i18n/locales/zh.json
dataset_format_converter-1.0.1.2.dist-info/licenses/LICENSE
dataset_format_converter-1.0.1.2.dist-info/METADATA
dataset_format_converter-1.0.1.2.dist-info/WHEEL
dataset_format_converter-1.0.1.2.dist-info/entry_points.txt
dataset_format_converter-1.0.1.2.dist-info/top_level.txt
dataset_format_converter-1.0.1.2.dist-info/RECORD
