Metadata-Version: 2.4
Name: dataset-format-converter
Version: 1.0.1.2
Summary: 多格式数据集标注转换工具 - Multi-format dataset annotation converter
Author-email: Blake Zhu <2112304124@mail2.gdut.edu.cn>
Maintainer-email: Blake Zhu <2112304124@mail2.gdut.edu.cn>
License-Expression: MIT
Project-URL: Homepage, https://github.com/BIANG-qilie/dataset-format-converter
Project-URL: Documentation, https://github.com/BIANG-qilie/dataset-format-converter#readme
Project-URL: Repository, https://github.com/BIANG-qilie/dataset-format-converter.git
Project-URL: Bug Tracker, https://github.com/BIANG-qilie/dataset-format-converter/issues
Keywords: yolo,obb,object-detection,computer-vision,annotation-tool,dota,labelimg,pascal-voc
Classifier: Development Status :: 4 - Beta
Classifier: Intended Audience :: Developers
Classifier: Intended Audience :: Science/Research
Classifier: Operating System :: OS Independent
Classifier: Programming Language :: Python :: 3
Classifier: Programming Language :: Python :: 3.6
Classifier: Programming Language :: Python :: 3.7
Classifier: Programming Language :: Python :: 3.8
Classifier: Programming Language :: Python :: 3.9
Classifier: Programming Language :: Python :: 3.10
Classifier: Programming Language :: Python :: 3.11
Classifier: Topic :: Scientific/Engineering :: Artificial Intelligence
Classifier: Topic :: Software Development :: Libraries :: Python Modules
Requires-Python: >=3.6
License-File: LICENSE
Requires-Dist: numpy>=1.19.0
Requires-Dist: pillow>=8.0.0
Requires-Dist: dataclasses>=0.8; python_version < "3.7"
Provides-Extra: dev
Requires-Dist: pytest>=6.0.0; extra == "dev"
Requires-Dist: pytest-cov>=2.0.0; extra == "dev"
Requires-Dist: black>=21.0.0; extra == "dev"
Requires-Dist: flake8>=3.8.0; extra == "dev"
Requires-Dist: mypy>=0.812; extra == "dev"
Requires-Dist: pre-commit>=2.15.0; extra == "dev"
Provides-Extra: gui
Requires-Dist: pillow>=8.0.0; extra == "gui"
Requires-Dist: tkinter; extra == "gui"
Provides-Extra: test
Requires-Dist: pytest>=6.0.0; extra == "test"
Requires-Dist: pytest-cov>=2.0.0; extra == "test"
Requires-Dist: pytest-mock>=3.6.0; extra == "test"
Dynamic: license-file
